ok_logging_setup/__init__.py
ok_logging_setup/_exit.py
ok_logging_setup/_filter.py
ok_logging_setup/_formatter.py
ok_logging_setup/_install.py
ok_logging_setup/py.typed
ok_logging_setup-0.12.dist-info/WHEEL
ok_logging_setup-0.12.dist-info/METADATA
ok_logging_setup-0.12.dist-info/RECORD
