Metadata-Version: 2.3
Name: ok-logging-setup
Version: 0.12
Summary: Simple minimalist Python logging defaults
Author: Dan Egnor
Author-email: Dan Egnor <egnor@ofb.net>
Requires-Python: >=3.10
Project-URL: Homepage, https://github.com/egnor/ok-py-logging-setup#readme
Project-URL: Repository, https://github.com/egnor/ok-py-logging-setup.git
